MANIFEST.in
README.rst
setup.py
ilang/Display.py
ilang/Graphs.py
ilang/Models.py
ilang/Samplers.py
ilang/Sources.py
ilang/Tracers.py
ilang/__init__.py
ilang/accessories.py
ilang/exceptions.py
ilang/verbose.py
ilang.egg-info/PKG-INFO
ilang.egg-info/SOURCES.txt
ilang.egg-info/dependency_links.txt
ilang.egg-info/requires.txt
ilang.egg-info/top_level.txt
ilang/examples/__init__.py
ilang/examples/gaussian.py
ilang/examples/spect.py
ilang/test/__init__.py
ilang/test/test_graphs.py
ilang/test/test_samplers.py
ilang/test/test_tracers.py